{
  "proof_written_at": "2026-05-20T14:37:33.486474+00:00",
  "correlation_id": "0cde9859-edd5-450e-ad76-48066503925d",
  "repo": "my-first-app",
  "transport_proof": {
    "request_id": "bd20bf6a-1a19-4563-9061-e7b88ca89227",
    "idempotency_key": null,
    "operation_class": "READ_ONLY",
    "command_name": "context.compile",
    "attempt_count": 1,
    "final_client_observation": "executed",
    "server_request_id": "49c4c2c8-aadb-416e-9b36-8862fb143a81",
    "original_request_id": null,
    "attempts": [
      {
        "attempt": 1,
        "request_id": "bd20bf6a-1a19-4563-9061-e7b88ca89227",
        "timestamp": "2026-05-20T14:37:32.710970+00:00",
        "reason": "",
        "delay_ms": 0
      }
    ],
    "retry_reasons": []
  }
}
